geotest/__init__.py
geotest/__main__.py
geotest-0.0.6.dist-info/METADATA
geotest-0.0.6.dist-info/WHEEL
geotest-0.0.6.dist-info/entry_points.txt
geotest-0.0.6.dist-info/RECORD
