Metadata-Version: 2.3
Name: geotest
Version: 0.0.6
Summary: This is a test package for automated package deployment using github actions
Author-email: geovicco-dev <geovicco.dev@gmail.com>
License-Expression: MIT
Requires-Python: >=3.8
Requires-Dist: typer>=0.12.3
